phantasyRestClient/__init__.py
phantasyRestClient/config/__init__.py
phantasyRestClient/config/client.ini
phantasyRestClient/config/client_ftc.ini
phantasyRestClient/config/read.py
phantasyRestClient/config/write.py
phantasyRestClient/req/__init__.py
phantasyRestClient/req/ca.py
phantasyRestClient/req/mp.py
phantasyRestClient/req/phy.py
phantasyRestClient/tests/__init__.py
phantasyRestClient/tests/test_mp.py
phantasyRestClient/tests/test_phy.py
phantasyRestClient-0.1.12.dist-info/LICENSE
phantasyRestClient-0.1.12.dist-info/METADATA
phantasyRestClient-0.1.12.dist-info/WHEEL
phantasyRestClient-0.1.12.dist-info/top_level.txt
phantasyRestClient-0.1.12.dist-info/RECORD
